presidio_image_redactor_pai_mirror/__init__.py
presidio_image_redactor_pai_mirror/bbox.py
presidio_image_redactor_pai_mirror/dicom_image_pii_verify_engine.py
presidio_image_redactor_pai_mirror/dicom_image_redactor_engine.py
presidio_image_redactor_pai_mirror/document_intelligence_ocr.py
presidio_image_redactor_pai_mirror/entities/__init__.py
presidio_image_redactor_pai_mirror/entities/api_request_convertor.py
presidio_image_redactor_pai_mirror/entities/image_recognizer_result.py
presidio_image_redactor_pai_mirror/entities/invalid_exception.py
presidio_image_redactor_pai_mirror/image_analyzer_engine.py
presidio_image_redactor_pai_mirror/image_pii_verify_engine.py
presidio_image_redactor_pai_mirror/image_processing_engine.py
presidio_image_redactor_pai_mirror/image_redactor_engine.py
presidio_image_redactor_pai_mirror/ocr.py
presidio_image_redactor_pai_mirror/py.typed
presidio_image_redactor_pai_mirror/tesseract_ocr.py
presidio_image_redactor_pai_mirror-0.0.54.dist-info/METADATA
presidio_image_redactor_pai_mirror-0.0.54.dist-info/WHEEL
presidio_image_redactor_pai_mirror-0.0.54.dist-info/RECORD
