Metadata-Version: 2.1
Name: presidio-image-redactor-pai-mirror
Version: 0.0.54
Summary: Presidio image redactor package MIRRORED FOR PAI. NOT MEANT FOR GENERAL USE.
License: MIT
Author: Presidio
Author-email: presidio@microsoft.com
Requires-Python: >=3.8,<4.0
Classifier: License :: OSI Approved :: MIT License
Classifier: Operating System :: OS Independent
Classifier: Programming Language :: Python :: 3
Classifier: Programming Language :: Python :: 3.8
Classifier: Programming Language :: Python :: 3.9
Classifier: Programming Language :: Python :: 3.10
Classifier: Programming Language :: Python :: 3.11
Classifier: Programming Language :: Python :: 3.12
Provides-Extra: server
Requires-Dist: azure-ai-formrecognizer (>=3.3.0,<4.0.0)
Requires-Dist: flask (>=1.1) ; extra == "server"
Requires-Dist: matplotlib (>=3.6)
Requires-Dist: opencv-python (>=4.0.0,<5.0.0)
Requires-Dist: pillow (>=9.0)
Requires-Dist: presidio-analyzer (>=1.9.0)
Requires-Dist: pydicom (>=2.3.0)
Requires-Dist: pypng (>=0.20220715.0)
Requires-Dist: pytesseract (>=0.3.7,<0.4)
Requires-Dist: python-gdcm (>=3.0.24.1)
Project-URL: Homepage, https://github.com/Microsoft/presidio
